{"cameraMode":{"drawMode":0,"name":"Shaded","section":"Shading Mode"},"sceneLighting":true,"audioPlay":false,"sceneViewState":{"m_AlwaysRefresh":false,"showFog":true,"showSkybox":true,"showFlares":true,"showImageEffects":true,"showParticleSystems":true,"showVisualEffectGraphs":true,"m_FxEnabled":true},"in2DMode":false,"pivot":{"x":2.014808177947998,"y":2.9186980724334719,"z":-0.03852701187133789},"rotation":{"x":0.21108846366405488,"y":0.7703931927680969,"z":-0.31870219111442568,"w":0.510261058807373},"size":10.0,"orthographic":false}